netbox_ip_permissions_synchronization/__init__.py
netbox_ip_permissions_synchronization/_version.py
netbox_ip_permissions_synchronization/forms.py
netbox_ip_permissions_synchronization/template_content.py
netbox_ip_permissions_synchronization/urls.py
netbox_ip_permissions_synchronization/utils.py
netbox_ip_permissions_synchronization/views.py
netbox_ip_permissions_synchronization/templates/netbox_ip_permissions_synchronization/ip_permissions_sync.html
netbox_ip_permissions_synchronization/templates/netbox_ip_permissions_synchronization/sync_ip_permissions_button.html
netbox_ip_permissions_synchronization-0.0.15.dist-info/licenses/LICENSE
netbox_ip_permissions_synchronization-0.0.15.dist-info/METADATA
netbox_ip_permissions_synchronization-0.0.15.dist-info/WHEEL
netbox_ip_permissions_synchronization-0.0.15.dist-info/top_level.txt
netbox_ip_permissions_synchronization-0.0.15.dist-info/RECORD
