Metadata-Version: 2.4
Name: netbox_ip_permissions_synchronization
Version: 0.0.15
Summary: Syncing permissions on IP Addresses with those from their corresponding Prefix in NetBox
Home-page: https://github.com/LoH-lu/netbox_ip_permissions_synchronization/
Author: Loris Henrion
Author-email: loris_henrion@bce.lu
License: GPL-3.0
License-File: LICENSE
Dynamic: author
Dynamic: author-email
Dynamic: description
Dynamic: description-content-type
Dynamic: home-page
Dynamic: license
Dynamic: license-file
Dynamic: summary
